django_dynamic_db_router-0.3.0.dist-info/DESCRIPTION.rst
django_dynamic_db_router-0.3.0.dist-info/METADATA
django_dynamic_db_router-0.3.0.dist-info/metadata.json
django_dynamic_db_router-0.3.0.dist-info/RECORD
django_dynamic_db_router-0.3.0.dist-info/top_level.txt
django_dynamic_db_router-0.3.0.dist-info/WHEEL
dynamic_db_router/__init__.py
dynamic_db_router/router.py
dynamic_db_router/version.py
dynamic_db_router/tests/__init__.py
dynamic_db_router/tests/models.py
dynamic_db_router/tests/tests.py
