Metadata-Version: 2.0
Name: django-dynamic-db-router
Version: 0.3.0
Summary: Simply route complex django queries to multiple databases.
Home-page: https://github.com/ambitioninc/django-dynamic-db-router
Author: Erik Swanson
Author-email: opensource@ambition.com
License: MIT
Platform: UNKNOWN
Classifier: Programming Language :: Python :: 2.7
Classifier: Programming Language :: Python :: 3.4
Classifier: Programming Language :: Python :: 3.5
Classifier: Intended Audience :: Developers
Classifier: License :: OSI Approved :: MIT License
Classifier: Operating System :: OS Independent
Requires-Dist: django (>=1.7)
